promptengine_ai/__init__.py
promptengine_ai/config.py
promptengine_ai/prompt_engine.py
promptengine_ai/utils.py
promptengine_ai-0.0.2.dist-info/LICENSE
promptengine_ai-0.0.2.dist-info/METADATA
promptengine_ai-0.0.2.dist-info/WHEEL
promptengine_ai-0.0.2.dist-info/top_level.txt
promptengine_ai-0.0.2.dist-info/RECORD
