Metadata-Version: 2.1
Name: promptengine-ai
Version: 0.0.2
Summary: PromptEngine is a Python library for conducting interview sessions using OpenAI's ChatGPT model.
Author: Bharat Bodkhe
Author-email: akybharat02@gmail.com
Keywords: python,interview,chatbot,AI
Classifier: Development Status :: 1 - Planning
Classifier: Intended Audience :: Developers
Classifier: Programming Language :: Python :: 3
Classifier: Operating System :: Unix
Classifier: Operating System :: MacOS :: MacOS X
Classifier: Operating System :: Microsoft :: Windows
License-File: LICENSE
Requires-Dist: openai
Requires-Dist: redis
Requires-Dist: tiktoken
Requires-Dist: requests
Requires-Dist: python-dotenv
Requires-Dist: pydub
